zitadel_client/__init__.py
zitadel_client/api/.openapi
zitadel_client/api/__init__.py
zitadel_client/api/action_service_api.py
zitadel_client/api/feature_service_api.py
zitadel_client/api/identity_provider_service_api.py
zitadel_client/api/oidc_service_api.py
zitadel_client/api/organization_service_api.py
zitadel_client/api/saml_service_api.py
zitadel_client/api/session_service_api.py
zitadel_client/api/settings_service_api.py
zitadel_client/api/user_service_api.py
zitadel_client/api/web_key_service_api.py
zitadel_client/api_client.py
zitadel_client/api_response.py
zitadel_client/auth/__init__.py
zitadel_client/auth/authenticator.py
zitadel_client/auth/client_credentials_authenticator.py
zitadel_client/auth/no_auth_authenticator.py
zitadel_client/auth/oauth_authenticator.py
zitadel_client/auth/open_id.py
zitadel_client/auth/personal_access_token_authenticator.py
zitadel_client/auth/web_token_authenticator.py
zitadel_client/configuration.py
zitadel_client/exceptions.py
zitadel_client/models/.openapi
zitadel_client/models/__init__.py
zitadel_client/models/action_service_beta_condition.py
zitadel_client/models/action_service_beta_create_target_response.py
zitadel_client/models/action_service_beta_delete_target_response.py
zitadel_client/models/action_service_beta_event_execution.py
zitadel_client/models/action_service_beta_execution.py
zitadel_client/models/action_service_beta_function_execution.py
zitadel_client/models/action_service_beta_get_target_response.py
zitadel_client/models/action_service_beta_in_target_ids_filter.py
zitadel_client/models/action_service_beta_list_execution_functions_response.py
zitadel_client/models/action_service_beta_list_execution_methods_response.py
zitadel_client/models/action_service_beta_list_execution_services_response.py
zitadel_client/models/action_service_beta_list_executions_response.py
zitadel_client/models/action_service_beta_list_targets_response.py
zitadel_client/models/action_service_beta_pagination_request.py
zitadel_client-1.7.0.dist-info/LICENSE
zitadel_client-1.7.0.dist-info/METADATA
zitadel_client-1.7.0.dist-info/WHEEL
zitadel_client-1.7.0.dist-info/RECORD
