Metadata-Version: 2.3
Name: zitadel_client
Version: 1.7.0
Summary: Official Zitadel SDK for Python. Authenticate and access Zitadel's authentication and management APIs in Python.
License: Apache-2.0
Keywords: sdk,iam,client-lib,client-library,sdk-python,zitadel,zitadel-sdk
Author: Mridang Agarwalla
Author-email: mridang@zitadel.com
Requires-Python: >=3.8, !=3.9.0, !=3.9.1
Classifier: Topic :: Software Development :: Libraries
Requires-Dist: authlib (==1.3.2)
Requires-Dist: cryptography (>=44.0.1,<45.0.0)
Requires-Dist: pydantic (>=2)
Requires-Dist: python-dateutil (>=2.8.2)
Requires-Dist: requests (>=2.32.3,<3.0.0)
Requires-Dist: typing-extensions (>=4.7.1)
Requires-Dist: urllib3 (>=1.25.3,<3.0.0)
Project-URL: Bug Tracker, https://github.com/zitadel/client-python/issues
Project-URL: Documentation, https://python-poetry.org/docs/
Project-URL: Homepage, https://zitadel.com/
Project-URL: Repository, https://github.com/zitadel/client-python
